django_stomp/__init__.py
django_stomp/apps.py
django_stomp/builder.py
django_stomp/exceptions.py
django_stomp/execution.py
django_stomp/helpers.py
django_stomp/settings.py
django_stomp/management/__init__.py
django_stomp/management/commands/__init__.py
django_stomp/management/commands/ack_all_messages.py
django_stomp/management/commands/move_messages.py
django_stomp/management/commands/pubsub.py
django_stomp/services/__init__.py
django_stomp/services/consumer.py
django_stomp/services/producer.py
django_stomp-6.1.0.dist-info/LICENSE
django_stomp-6.1.0.dist-info/METADATA
django_stomp-6.1.0.dist-info/WHEEL
django_stomp-6.1.0.dist-info/top_level.txt
django_stomp-6.1.0.dist-info/RECORD
