Metadata-Version: 2.1
Name: django-stomp
Version: 6.1.0
Summary: A simple implementation of STOMP with Django
Home-page: https://github.com/juntossomosmais/django-stomp
Author: Ricardo Baltazar Chaves, Willian Antunes
Author-email: Ricardo Baltazar <ricardobchaves6@gmail.com>, Willian Antunes <willian.lima.antunes@gmail.com>
License: MIT
Classifier: Programming Language :: Python
Classifier: Programming Language :: Python :: 3.10
Classifier: Framework :: Django :: 5.1
Classifier: Environment :: Web Environment
Classifier: Natural Language :: Portuguese (Brazilian)
Classifier: Development Status :: 5 - Production/Stable
Classifier: Framework :: Django
Classifier: Intended Audience :: Developers
Classifier: License :: OSI Approved :: MIT License
Classifier: Operating System :: OS Independent
License-File: LICENSE
Requires-Dist: request-id-django-log==0.2.0
Requires-Dist: stomp.py~=8.0
Requires-Dist: tenacity~=8.0
